{
  "total": 15197,
  "total_pages": 1520,
  "results": [
    {
      "id": "70l1tDAI6rM",
      "created_at": "2018-05-05T01:31:41-04:00",
      "updated_at": "2018-09-21T14:14:53-04:00",
      "width": 3024,
      "height": 4032,
      "color": "#09130A",
      "description": "green leaves",
      "urls": {
        "raw": "https://images.unsplash.com/photo-1525498128493-380d1990a112?ixlib=rb-0.3.5&ixid=eyJhcHBfaWQiOjQwNDY1fQ&s=911233fd2a9c78afbd4d6231f0d43b67",
        "full": "https://images.unsplash.com/photo-1525498128493-380d1990a112?ixlib=rb-0.3.5&q=85&fm=jpg&crop=entropy&cs=srgb&ixid=eyJhcHBfaWQiOjQwNDY1fQ&s=8f861295e3ada9ed8c364bc62f1320be",
        "regular": "https://images.unsplash.com/photo-1525498128493-380d1990a112?ixlib=rb-0.3.5&q=80&fm=jpg&crop=entropy&cs=tinysrgb&w=1080&fit=max&ixid=eyJhcHBfaWQiOjQwNDY1fQ&s=ce9f4f058b6c10c90aea7a84c05a083e",
        "small": "https://images.unsplash.com/photo-1525498128493-380d1990a112?ixlib=rb-0.3.5&q=80&fm=jpg&crop=entropy&cs=tinysrgb&w=400&fit=max&ixid=eyJhcHBfaWQiOjQwNDY1fQ&s=f851cab4feda3927ab82bdf07b87c14f",
        "thumb": "https://images.unsplash.com/photo-1525498128493-380d1990a112?ixlib=rb-0.3.5&q=80&fm=jpg&crop=entropy&cs=tinysrgb&w=200&fit=max&ixid=eyJhcHBfaWQiOjQwNDY1fQ&s=69afc66d00071b5830e301374a7d90ad"
      },
      "links": {
        "self": "https://api.unsplash.com/photos/70l1tDAI6rM",
        "html": "https://unsplash.com/photos/70l1tDAI6rM",
        "download": "https://unsplash.com/photos/70l1tDAI6rM/download",
        "download_location": "https://api.unsplash.com/photos/70l1tDAI6rM/download"
      },
      "categories": [],
      "sponsored": false,
      "sponsored_by": null,
      "sponsored_impressions_id": null,
      "likes": 779,
      "liked_by_user": false,
      "current_user_collections": [],
      "slug": null,
      "user": {
        "id": "Ib8exzXFC2Y",
        "updated_at": "2018-10-26T11:23:51-04:00",
        "username": "chrisleeiam",
        "name": "Chris Lee",
        "first_name": "Chris",
        "last_name": "Lee",
        "twitter_username": "chrisleeiam",
        "portfolio_url": null,
        "bio": null,
        "location": "MX",
        "links": {
          "self": "https://api.unsplash.com/users/chrisleeiam",
          "html": "https://unsplash.com/@chrisleeiam",
          "photos": "https://api.unsplash.com/users/chrisleeiam/photos",
          "likes": "https://api.unsplash.com/users/chrisleeiam/likes",
          "portfolio": "https://api.unsplash.com/users/chrisleeiam/portfolio",
          "following": "https://api.unsplash.com/users/chrisleeiam/following",
          "followers": "https://api.unsplash.com/users/chrisleeiam/followers"
        },
        "profile_image": {
          "small": "https://images.unsplash.com/profile-1444150880999-8042a8ce0979?ixlib=rb-0.3.5&q=80&fm=jpg&crop=faces&cs=tinysrgb&fit=crop&h=32&w=32&s=a19248eb27010a89557b8976bc63dbbc",
          "medium": "https://images.unsplash.com/profile-1444150880999-8042a8ce0979?ixlib=rb-0.3.5&q=80&fm=jpg&crop=faces&cs=tinysrgb&fit=crop&h=64&w=64&s=f0c7f03e3eb53cf672e41335d1ae78b5",
          "large": "https://images.unsplash.com/profile-1444150880999-8042a8ce0979?ixlib=rb-0.3.5&q=80&fm=jpg&crop=faces&cs=tinysrgb&fit=crop&h=128&w=128&s=0e5c358a66770755f016bca86f02886c"
        },
        "instagram_username": "chrisleeiam",
        "total_collections": 0,
        "total_likes": 10,
        "total_photos": 4,
        "accepted_tos": false
      },
      "tags": [
        {
          "title": "greem"
        },
        {
          "title": "leaf"
        },
        {
          "title": "plant"
        },
        {
          "title": "indoors"
        },
        {
          "title": "stem"
        },
        {
          "title": "leaves"
        },
        {
          "title": "veins"
        },
        {
          "title": "interior"
        },
        {
          "title": "white"
        },
        {
          "title": "nature"
        },
        {
          "title": "green"
        },
        {
          "title": "cheese plant"
        },
        {
          "title": "ceriman"
        },
        {
          "title": "fruit salad plant"
        },
        {
          "title": "monstera deliciosa"
        },
        {
          "title": "#wallpaper"
        },
        {
          "title": "elegant"
        },
        {
          "title": "boho"
        },
        {
          "title": "monstera"
        }
      ],
      "photo_tags": [
        {
          "title": "greem"
        },
        {
          "title": "leaf"
        },
        {
          "title": "plant"
        },
        {
          "title": "indoors"
        },
        {
          "title": "stem"
        }
      ]
    },
    {
      "id": "d2zvqp3fpro",
      "created_at": "2018-06-01T21:43:38-04:00",
      "updated_at": "2018-09-05T22:56:06-04:00",
      "width": 5651,
      "height": 4000,
      "color": "#141A16",
      "description": "floral artwork on surface",
      "urls": {
        "raw": "https://images.unsplash.com/photo-1527903789995-dc8ad2ad6de0?ixlib=rb-0.3.5&ixid=eyJhcHBfaWQiOjQwNDY1fQ&s=08eece4547c88a2cd9d06e58ddd1a494",
        "full": "https://images.unsplash.com/photo-1527903789995-dc8ad2ad6de0?ixlib=rb-0.3.5&q=85&fm=jpg&crop=entropy&cs=srgb&ixid=eyJhcHBfaWQiOjQwNDY1fQ&s=aab7518dc3aed42e9729ace9ddba8a6c",
        "regular": "https://images.unsplash.com/photo-1527903789995-dc8ad2ad6de0?ixlib=rb-0.3.5&q=80&fm=jpg&crop=entropy&cs=tinysrgb&w=1080&fit=max&ixid=eyJhcHBfaWQiOjQwNDY1fQ&s=b9eb5b83ac8c8ea550194ed803eb4d41",
        "small": "https://images.unsplash.com/photo-1527903789995-dc8ad2ad6de0?ixlib=rb-0.3.5&q=80&fm=jpg&crop=entropy&cs=tinysrgb&w=400&fit=max&ixid=eyJhcHBfaWQiOjQwNDY1fQ&s=1ae777633aa8d9c4e320bd2ea5337ec2",
        "thumb": "https://images.unsplash.com/photo-1527903789995-dc8ad2ad6de0?ixlib=rb-0.3.5&q=80&fm=jpg&crop=entropy&cs=tinysrgb&w=200&fit=max&ixid=eyJhcHBfaWQiOjQwNDY1fQ&s=42aac2baec114ee765b52aebce2cd851"
      },
      "links": {
        "self": "https://api.unsplash.com/photos/d2zvqp3fpro",
        "html": "https://unsplash.com/photos/d2zvqp3fpro",
        "download": "https://unsplash.com/photos/d2zvqp3fpro/download",
        "download_location": "https://api.unsplash.com/photos/d2zvqp3fpro/download"
      },
      "categories": [],
      "sponsored": false,
      "sponsored_by": null,
      "sponsored_impressions_id": null,
      "likes": 141,
      "liked_by_user": false,
      "current_user_collections": [],
      "slug": null,
      "user": {
        "id": "ZHBe6w44Tt8",
        "updated_at": "2018-10-28T05:09:25-04:00",
        "username": "creativeexchange",
        "name": "The Creative Exchange",
        "first_name": "The Creative Exchange",
        "last_name": null,
        "twitter_username": "creative_xchnge",
        "portfolio_url": "https://www.thecreativeexchange.co/",
        "bio": "We are a content studio + social media agency. Rated No. 3 on Agency Spotter's Top 20 Social Media Agencies of 2018.",
        "location": "Washington, DC",
        "links": {
          "self": "https://api.unsplash.com/users/creativeexchange",
          "html": "https://unsplash.com/@creativeexchange",
          "photos": "https://api.unsplash.com/users/creativeexchange/photos",
          "likes": "https://api.unsplash.com/users/creativeexchange/likes",
          "portfolio": "https://api.unsplash.com/users/creativeexchange/portfolio",
          "following": "https://api.unsplash.com/users/creativeexchange/following",
          "followers": "https://api.unsplash.com/users/creativeexchange/followers"
        },
        "profile_image": {
          "small": "https://images.unsplash.com/profile-1527216316813-61fd1d5115bb?ixlib=rb-0.3.5&q=80&fm=jpg&crop=faces&cs=tinysrgb&fit=crop&h=32&w=32&s=93c08e4ba535782b2d441068f34b5df3",
          "medium": "https://images.unsplash.com/profile-1527216316813-61fd1d5115bb?ixlib=rb-0.3.5&q=80&fm=jpg&crop=faces&cs=tinysrgb&fit=crop&h=64&w=64&s=3e232b061f04a1e5674828a5c6ff694d",
          "large": "https://images.unsplash.com/profile-1527216316813-61fd1d5115bb?ixlib=rb-0.3.5&q=80&fm=jpg&crop=faces&cs=tinysrgb&fit=crop&h=128&w=128&s=66ead02cf6f11adf1f2a5739306b4602"
        },
        "instagram_username": "thecreative_exchange",
        "total_collections": 3,
        "total_likes": 0,
        "total_photos": 58,
        "accepted_tos": false
      },
      "tags": [
        {
          "title": "petal"
        },
        {
          "title": "floral"
        },
        {
          "title": "flat lay"
        },
        {
          "title": "natural"
        },
        {
          "title": "plant"
        },
        {
          "title": "flatlay"
        },
        {
          "title": "blossom"
        },
        {
          "title": "dired flower"
        },
        {
          "title": "stem"
        },
        {
          "title": "art"
        },
        {
          "title": "white background"
        },
        {
          "title": "minimalist"
        },
        {
          "title": "white"
        },
        {
          "title": "flower"
        },
        {
          "title": "contrast"
        },
        {
          "title": "bud"
        },
        {
          "title": "blosson"
        },
        {
          "title": "dried flower"
        }
      ],
      "photo_tags": [
        {
          "title": "petal"
        },
        {
          "title": "floral"
        },
        {
          "title": "flat lay"
        },
        {
          "title": "natural"
        },
        {
          "title": "plant"
        }
      ]
    },
    {
      "id": "oBb-Y26PJgg",
      "created_at": "2017-09-16T07:45:36-04:00",
      "updated_at": "2018-08-28T20:23:21-04:00",
      "width": 5904,
      "height": 3936,
      "color": "#3C3F41",
      "description": "unfinished wall paint",
      "urls": {
        "raw": "https://images.unsplash.com/photo-1505562130589-9879683e72da?ixlib=rb-0.3.5&ixid=eyJhcHBfaWQiOjQwNDY1fQ&s=df4e6be90cecbd710bc378d8e65b60ed",
        "full": "https://images.unsplash.com/photo-1505562130589-9879683e72da?ixlib=rb-0.3.5&q=85&fm=jpg&crop=entropy&cs=srgb&ixid=eyJhcHBfaWQiOjQwNDY1fQ&s=b771dce51f3a072059abee7808025347",
        "regular": "https://images.unsplash.com/photo-1505562130589-9879683e72da?ixlib=rb-0.3.5&q=80&fm=jpg&crop=entropy&cs=tinysrgb&w=1080&fit=max&ixid=eyJhcHBfaWQiOjQwNDY1fQ&s=a71476e163657912154255c702df58ed",
        "small": "https://images.unsplash.com/photo-1505562130589-9879683e72da?ixlib=rb-0.3.5&q=80&fm=jpg&crop=entropy&cs=tinysrgb&w=400&fit=max&ixid=eyJhcHBfaWQiOjQwNDY1fQ&s=ab23f9a77b3d5d77fd88324b0dfcb6cc",
        "thumb": "https://images.unsplash.com/photo-1505562130589-9879683e72da?ixlib=rb-0.3.5&q=80&fm=jpg&crop=entropy&cs=tinysrgb&w=200&fit=max&ixid=eyJhcHBfaWQiOjQwNDY1fQ&s=af7e47f4ce87e6f02bd3781100870377"
      },
      "links": {
        "self": "https://api.unsplash.com/photos/oBb-Y26PJgg",
        "html": "https://unsplash.com/photos/oBb-Y26PJgg",
        "download": "https://unsplash.com/photos/oBb-Y26PJgg/download",
        "download_location": "https://api.unsplash.com/photos/oBb-Y26PJgg/download"
      },
      "categories": [],
      "sponsored": false,
      "sponsored_by": null,
      "sponsored_impressions_id": null,
      "likes": 2067,
      "liked_by_user": false,
      "current_user_collections": [],
      "slug": null,
      "user": {
        "id": "gnwb2chNB0Q",
        "updated_at": "2018-10-28T07:36:18-04:00",
        "username": "samuelzeller",
        "name": "Samuel Zeller",
        "first_name": "Samuel",
        "last_name": "Zeller",
        "twitter_username": "zellersamuel",
        "portfolio_url": "https://samuelzeller.ch",
        "bio": "Swiss freelance photographer based in Geneva. Available for work. Prints and book on my website. For inquiries: sam@samuelzeller.ch - Instagram @zellersamuel",
        "location": "Geneva, Switzerland",
        "links": {
          "self": "https://api.unsplash.com/users/samuelzeller",
          "html": "https://unsplash.com/@samuelzeller",
          "photos": "https://api.unsplash.com/users/samuelzeller/photos",
          "likes": "https://api.unsplash.com/users/samuelzeller/likes",
          "portfolio": "https://api.unsplash.com/users/samuelzeller/portfolio",
          "following": "https://api.unsplash.com/users/samuelzeller/following",
          "followers": "https://api.unsplash.com/users/samuelzeller/followers"
        },
        "profile_image": {
          "small": "https://images.unsplash.com/profile-1513085354324-db40f48c30ed?ixlib=rb-0.3.5&q=80&fm=jpg&crop=faces&cs=tinysrgb&fit=crop&h=32&w=32&s=2d5447565a9aa2a27d0dcd7c35aea472",
          "medium": "https://images.unsplash.com/profile-1513085354324-db40f48c30ed?ixlib=rb-0.3.5&q=80&fm=jpg&crop=faces&cs=tinysrgb&fit=crop&h=64&w=64&s=0718318990d75df64123408629e720bd",
          "large": "https://images.unsplash.com/profile-1513085354324-db40f48c30ed?ixlib=rb-0.3.5&q=80&fm=jpg&crop=faces&cs=tinysrgb&fit=crop&h=128&w=128&s=5bf14a6e2bd467e9a7b6ee1cadaaf363"
        },
        "instagram_username": "zellersamuel",
        "total_collections": 15,
        "total_likes": 4,
        "total_photos": 501,
        "accepted_tos": false
      },
      "tags": [
        {
          "title": "paint"
        },
        {
          "title": "wall"
        },
        {
          "title": "paint stroke"
        },
        {
          "title": "flat color"
        },
        {
          "title": "painting wall"
        },
        {
          "title": "white"
        },
        {
          "title": "grey"
        },
        {
          "title": "color"
        },
        {
          "title": "background"
        },
        {
          "title": "texture"
        },
        {
          "title": "paint brush"
        },
        {
          "title": "abstract"
        },
        {
          "title": "minimalist"
        },
        {
          "title": "minimalism"
        },
        {
          "title": "gray"
        },
        {
          "title": "flat"
        }
      ],
      "photo_tags": [
        {
          "title": "paint"
        },
        {
          "title": "wall"
        },
        {
          "title": "paint stroke"
        },
        {
          "title": "flat color"
        },
        {
          "title": "painting wall"
        }
      ]
    },
    {
      "id": "WmmcTOe3vqA",
      "created_at": "2018-04-22T10:49:56-04:00",
      "updated_at": "2018-08-28T21:00:09-04:00",
      "width": 3515,
      "height": 5272,
      "color": "#096062",
      "description": "plane aerobatic",
      "urls": {
        "raw": "https://images.unsplash.com/photo-1524408504872-4d40d453c67f?ixlib=rb-0.3.5&ixid=eyJhcHBfaWQiOjQwNDY1fQ&s=b27ae03808c7074246a8d76c35a15a92",
        "full": "https://images.unsplash.com/photo-1524408504872-4d40d453c67f?ixlib=rb-0.3.5&q=85&fm=jpg&crop=entropy&cs=srgb&ixid=eyJhcHBfaWQiOjQwNDY1fQ&s=8d909848a91b44bb97fad46d1a55f102",
        "regular": "https://images.unsplash.com/photo-1524408504872-4d40d453c67f?ixlib=rb-0.3.5&q=80&fm=jpg&crop=entropy&cs=tinysrgb&w=1080&fit=max&ixid=eyJhcHBfaWQiOjQwNDY1fQ&s=60590f291101f62bce8fcc14af8dda67",
        "small": "https://images.unsplash.com/photo-1524408504872-4d40d453c67f?ixlib=rb-0.3.5&q=80&fm=jpg&crop=entropy&cs=tinysrgb&w=400&fit=max&ixid=eyJhcHBfaWQiOjQwNDY1fQ&s=96eda1cd01447afcbbe138bb2dbf9156",
        "thumb": "https://images.unsplash.com/photo-1524408504872-4d40d453c67f?ixlib=rb-0.3.5&q=80&fm=jpg&crop=entropy&cs=tinysrgb&w=200&fit=max&ixid=eyJhcHBfaWQiOjQwNDY1fQ&s=a97b6cdc06637cdd35444bec666240bd"
      },
      "links": {
        "self": "https://api.unsplash.com/photos/WmmcTOe3vqA",
        "html": "https://unsplash.com/photos/WmmcTOe3vqA",
        "download": "https://unsplash.com/photos/WmmcTOe3vqA/download",
        "download_location": "https://api.unsplash.com/photos/WmmcTOe3vqA/download"
      },
      "categories": [],
      "sponsored": false,
      "sponsored_by": null,
      "sponsored_impressions_id": null,
      "likes": 261,
      "liked_by_user": false,
      "current_user_collections": [],
      "slug": null,
      "user": {
        "id": "mtszRgKv6MM",
        "updated_at": "2018-10-21T08:36:15-04:00",
        "username": "giantdesign",
        "name": "Ablimit Ablet",
        "first_name": "Ablimit",
        "last_name": "Ablet",
        "twitter_username": "Ablimitgiant",
        "portfolio_url": null,
        "bio": "Graphic Designer",
        "location": "Florence, Italy",
        "links": {
          "self": "https://api.unsplash.com/users/giantdesign",
          "html": "https://unsplash.com/@giantdesign",
          "photos": "https://api.unsplash.com/users/giantdesign/photos",
          "likes": "https://api.unsplash.com/users/giantdesign/likes",
          "portfolio": "https://api.unsplash.com/users/giantdesign/portfolio",
          "following": "https://api.unsplash.com/users/giantdesign/following",
          "followers": "https://api.unsplash.com/users/giantdesign/followers"
        },
        "profile_image": {
          "small": "https://images.unsplash.com/profile-1529962220648-b70128d2ce8e?ixlib=rb-0.3.5&q=80&fm=jpg&crop=faces&cs=tinysrgb&fit=crop&h=32&w=32&s=b5f053cd0d1d53d22935202e76f12e8a",
          "medium": "https://images.unsplash.com/profile-1529962220648-b70128d2ce8e?ixlib=rb-0.3.5&q=80&fm=jpg&crop=faces&cs=tinysrgb&fit=crop&h=64&w=64&s=f2136f41b11f745eaa38529dc5655df7",
          "large": "https://images.unsplash.com/profile-1529962220648-b70128d2ce8e?ixlib=rb-0.3.5&q=80&fm=jpg&crop=faces&cs=tinysrgb&fit=crop&h=128&w=128&s=a37d9ec1324f353050532c08679cffa0"
        },
        "instagram_username": "gigganit",
        "total_collections": 0,
        "total_likes": 4,
        "total_photos": 66,
        "accepted_tos": false
      },
      "tags": [
        {
          "title": "sky"
        },
        {
          "title": "plane"
        },
        {
          "title": "aeroplane"
        },
        {
          "title": "line"
        },
        {
          "title": "blue"
        },
        {
          "title": "smoke"
        },
        {
          "title": "gradient"
        },
        {
          "title": "minimalism"
        },
        {
          "title": "contrail"
        },
        {
          "title": "trail"
        },
        {
          "title": "fly"
        },
        {
          "title": "symmetry"
        },
        {
          "title": "mist"
        },
        {
          "title": "exhaust"
        },
        {
          "title": "airplane"
        },
        {
          "title": "bird"
        },
        {
          "title": "animal"
        },
        {
          "title": "vehicle"
        },
        {
          "title": "flight"
        },
        {
          "title": "color"
        }
      ],
      "photo_tags": [
        {
          "title": "sky"
        },
        {
          "title": "plane"
        },
        {
          "title": "aeroplane"
        },
        {
          "title": "line"
        },
        {
          "title": "blue"
        }
      ]
    },
    {
      "id": "_oNISBwMTwo",
      "created_at": "2018-01-14T04:48:29-05:00",
      "updated_at": "2018-08-28T20:39:14-04:00",
      "width": 5472,
      "height": 3648,
      "color": "#0A0A0A",
      "description": "three gray kingfisher birds",
      "urls": {
        "raw": "https://images.unsplash.com/photo-1515923152115-758a6b16f35e?ixlib=rb-0.3.5&ixid=eyJhcHBfaWQiOjQwNDY1fQ&s=fdefdad3b3755d1b1ecd1c460d2d2a12",
        "full": "https://images.unsplash.com/photo-1515923152115-758a6b16f35e?ixlib=rb-0.3.5&q=85&fm=jpg&crop=entropy&cs=srgb&ixid=eyJhcHBfaWQiOjQwNDY1fQ&s=56abdf048c40f7820e0198d6568120f3",
        "regular": "https://images.unsplash.com/photo-1515923152115-758a6b16f35e?ixlib=rb-0.3.5&q=80&fm=jpg&crop=entropy&cs=tinysrgb&w=1080&fit=max&ixid=eyJhcHBfaWQiOjQwNDY1fQ&s=09faa9bac83e917b3f93874bfd022e38",
        "small": "https://images.unsplash.com/photo-1515923152115-758a6b16f35e?ixlib=rb-0.3.5&q=80&fm=jpg&crop=entropy&cs=tinysrgb&w=400&fit=max&ixid=eyJhcHBfaWQiOjQwNDY1fQ&s=2ea605013fc08f1658409ac5fee5cc3b",
        "thumb": "https://images.unsplash.com/photo-1515923152115-758a6b16f35e?ixlib=rb-0.3.5&q=80&fm=jpg&crop=entropy&cs=tinysrgb&w=200&fit=max&ixid=eyJhcHBfaWQiOjQwNDY1fQ&s=cd7570195698b5549cdca08f4e62b5e7"
      },
      "links": {
        "self": "https://api.unsplash.com/photos/_oNISBwMTwo",
        "html": "https://unsplash.com/photos/_oNISBwMTwo",
        "download": "https://unsplash.com/photos/_oNISBwMTwo/download",
        "download_location": "https://api.unsplash.com/photos/_oNISBwMTwo/download"
      },
      "categories": [],
      "sponsored": false,
      "sponsored_by": null,
      "sponsored_impressions_id": null,
      "likes": 464,
      "liked_by_user": false,
      "current_user_collections": [],
      "slug": null,
      "user": {
        "id": "Yts8xMxIhJU",
        "updated_at": "2018-10-05T07:38:36-04:00",
        "username": "glencarrie",
        "name": "Glen Carrie",
        "first_name": "Glen",
        "last_name": "Carrie",
        "twitter_username": "CocoPineSA",
        "portfolio_url": "http://www.cocopine.co.za",
        "bio": "Love Family, Love Music , Love Football, Love Visuals, Love Fun, Love Life",
        "location": "Johannesburg , South Africa",
        "links": {
          "self": "https://api.unsplash.com/users/glencarrie",
          "html": "https://unsplash.com/@glencarrie",
          "photos": "https://api.unsplash.com/users/glencarrie/photos",
          "likes": "https://api.unsplash.com/users/glencarrie/likes",
          "portfolio": "https://api.unsplash.com/users/glencarrie/portfolio",
          "following": "https://api.unsplash.com/users/glencarrie/following",
          "followers": "https://api.unsplash.com/users/glencarrie/followers"
        },
        "profile_image": {
          "small": "https://images.unsplash.com/profile-1533811202405-8e780bdac032?ixlib=rb-0.3.5&q=80&fm=jpg&crop=faces&cs=tinysrgb&fit=crop&h=32&w=32&s=5e2c0ae36b27c8212d5ea884b31e0531",
          "medium": "https://images.unsplash.com/profile-1533811202405-8e780bdac032?ixlib=rb-0.3.5&q=80&fm=jpg&crop=faces&cs=tinysrgb&fit=crop&h=64&w=64&s=a52c78334da41a6d8a45a0e1c859f185",
          "large": "https://images.unsplash.com/profile-1533811202405-8e780bdac032?ixlib=rb-0.3.5&q=80&fm=jpg&crop=faces&cs=tinysrgb&fit=crop&h=128&w=128&s=7239b75a53cad4accc5c5cdda397f966"
        },
        "instagram_username": null,
        "total_collections": 2,
        "total_likes": 18,
        "total_photos": 120
      },
      "tags": [
        {
          "title": "bord"
        },
        {
          "title": "cable"
        },
        {
          "title": "wire"
        },
        {
          "title": "trio"
        },
        {
          "title": "white"
        },
        {
          "title": "wildlife"
        },
        {
          "title": "birding"
        },
        {
          "title": "bird"
        }
      ],
      "photo_tags": [
        {
          "title": "bord"
        },
        {
          "title": "cable"
        },
        {
          "title": "wire"
        },
        {
          "title": "trio"
        },
        {
          "title": "white"
        }
      ]
    },
    {
      "id": "BtnKPfzOinc",
      "created_at": "2018-03-19T00:32:09-04:00",
      "updated_at": "2018-08-28T20:54:40-04:00",
      "width": 2992,
      "height": 3992,
      "color": "#CCC1B0",
      "description": "brown wooden bridge on body of water",
      "urls": {
        "raw": "https://images.unsplash.com/photo-1521433849537-1d4ead3ddaf9?ixlib=rb-0.3.5&ixid=eyJhcHBfaWQiOjQwNDY1fQ&s=ddd1cd9c187288c210cecdbf3e21d37b",
        "full": "https://images.unsplash.com/photo-1521433849537-1d4ead3ddaf9?ixlib=rb-0.3.5&q=85&fm=jpg&crop=entropy&cs=srgb&ixid=eyJhcHBfaWQiOjQwNDY1fQ&s=7ce2815a07a4d545f90adc74280f142f",
        "regular": "https://images.unsplash.com/photo-1521433849537-1d4ead3ddaf9?ixlib=rb-0.3.5&q=80&fm=jpg&crop=entropy&cs=tinysrgb&w=1080&fit=max&ixid=eyJhcHBfaWQiOjQwNDY1fQ&s=9dae06b51a26923c5bca6b86cb5f2458",
        "small": "https://images.unsplash.com/photo-1521433849537-1d4ead3ddaf9?ixlib=rb-0.3.5&q=80&fm=jpg&crop=entropy&cs=tinysrgb&w=400&fit=max&ixid=eyJhcHBfaWQiOjQwNDY1fQ&s=e7a752cd4521c4adb4d4b1733d9338c2",
        "thumb": "https://images.unsplash.com/photo-1521433849537-1d4ead3ddaf9?ixlib=rb-0.3.5&q=80&fm=jpg&crop=entropy&cs=tinysrgb&w=200&fit=max&ixid=eyJhcHBfaWQiOjQwNDY1fQ&s=865a11fbedd49592abea978e9a47c171"
      },
      "links": {
        "self": "https://api.unsplash.com/photos/BtnKPfzOinc",
        "html": "https://unsplash.com/photos/BtnKPfzOinc",
        "download": "https://unsplash.com/photos/BtnKPfzOinc/download",
        "download_location": "https://api.unsplash.com/photos/BtnKPfzOinc/download"
      },
      "categories": [],
      "sponsored": false,
      "sponsored_by": null,
      "sponsored_impressions_id": null,
      "likes": 154,
      "liked_by_user": false,
      "current_user_collections": [],
      "slug": null,
      "user": {
        "id": "1EalmSI2GPQ",
        "updated_at": "2018-10-25T19:47:53-04:00",
        "username": "a2eorigins",
        "name": "Alex Perez",
        "first_name": "Alex",
        "last_name": "Perez",
        "twitter_username": "alexa2e",
        "portfolio_url": "http://A2EORIGINS.com",
        "bio": "Reaching for the Beyond!",
        "location": "Marco Island, Florida",
        "links": {
          "self": "https://api.unsplash.com/users/a2eorigins",
          "html": "https://unsplash.com/@a2eorigins",
          "photos": "https://api.unsplash.com/users/a2eorigins/photos",
          "likes": "https://api.unsplash.com/users/a2eorigins/likes",
          "portfolio": "https://api.unsplash.com/users/a2eorigins/portfolio",
          "following": "https://api.unsplash.com/users/a2eorigins/following",
          "followers": "https://api.unsplash.com/users/a2eorigins/followers"
        },
        "profile_image": {
          "small": "https://images.unsplash.com/profile-1517464280361-887314d56e6c?ixlib=rb-0.3.5&q=80&fm=jpg&crop=faces&cs=tinysrgb&fit=crop&h=32&w=32&s=56ba83a2f13baeb99797d6c03c48817e",
          "medium": "https://images.unsplash.com/profile-1517464280361-887314d56e6c?ixlib=rb-0.3.5&q=80&fm=jpg&crop=faces&cs=tinysrgb&fit=crop&h=64&w=64&s=7f30bc4a08e6dda727616b67dfd79d52",
          "large": "https://images.unsplash.com/profile-1517464280361-887314d56e6c?ixlib=rb-0.3.5&q=80&fm=jpg&crop=faces&cs=tinysrgb&fit=crop&h=128&w=128&s=27fdc9dafeed93e24dc74761000db85f"
        },
        "instagram_username": "A2EORIGINS",
        "total_collections": 0,
        "total_likes": 299,
        "total_photos": 113,
        "accepted_tos": false
      },
      "tags": [
        {
          "title": "pier"
        },
        {
          "title": "drone view"
        },
        {
          "title": "from above"
        },
        {
          "title": "beach"
        },
        {
          "title": "water"
        },
        {
          "title": "aerial"
        },
        {
          "title": "drone"
        },
        {
          "title": "ocean"
        },
        {
          "title": "island"
        },
        {
          "title": "nature"
        },
        {
          "title": "moody"
        },
        {
          "title": "deep waters"
        },
        {
          "title": "deep blue"
        },
        {
          "title": "water texture"
        },
        {
          "title": "minimal landscape"
        },
        {
          "title": "wooden pier"
        },
        {
          "title": "sunset"
        },
        {
          "title": "dji"
        }
      ],
      "photo_tags": [
        {
          "title": "pier"
        },
        {
          "title": "drone view"
        },
        {
          "title": "from above"
        },
        {
          "title": "beach"
        },
        {
          "title": "water"
        }
      ]
    },
    {
      "id": "Jrl_UQcZqOc",
      "created_at": "2018-03-05T10:08:24-05:00",
      "updated_at": "2018-08-28T20:52:04-04:00",
      "width": 3264,
      "height": 4896,
      "color": "#0B0B0B",
      "description": "photography of tree",
      "urls": {
        "raw": "https://images.unsplash.com/photo-1520262494112-9fe481d36ec3?ixlib=rb-0.3.5&ixid=eyJhcHBfaWQiOjQwNDY1fQ&s=8e83b13b6d1060b285fca7b413f9ea59",
        "full": "https://images.unsplash.com/photo-1520262494112-9fe481d36ec3?ixlib=rb-0.3.5&q=85&fm=jpg&crop=entropy&cs=srgb&ixid=eyJhcHBfaWQiOjQwNDY1fQ&s=d6e5a9c6021bf87ffd90745907d4fa0a",
        "regular": "https://images.unsplash.com/photo-1520262494112-9fe481d36ec3?ixlib=rb-0.3.5&q=80&fm=jpg&crop=entropy&cs=tinysrgb&w=1080&fit=max&ixid=eyJhcHBfaWQiOjQwNDY1fQ&s=25898084b9204e2f21ceaaaa5ae4dc1d",
        "small": "https://images.unsplash.com/photo-1520262494112-9fe481d36ec3?ixlib=rb-0.3.5&q=80&fm=jpg&crop=entropy&cs=tinysrgb&w=400&fit=max&ixid=eyJhcHBfaWQiOjQwNDY1fQ&s=32b741ddc583c91f9a29570efc55e31c",
        "thumb": "https://images.unsplash.com/photo-1520262494112-9fe481d36ec3?ixlib=rb-0.3.5&q=80&fm=jpg&crop=entropy&cs=tinysrgb&w=200&fit=max&ixid=eyJhcHBfaWQiOjQwNDY1fQ&s=115b2d2a2dd69184488c98564e82a449"
      },
      "links": {
        "self": "https://api.unsplash.com/photos/Jrl_UQcZqOc",
        "html": "https://unsplash.com/photos/Jrl_UQcZqOc",
        "download": "https://unsplash.com/photos/Jrl_UQcZqOc/download",
        "download_location": "https://api.unsplash.com/photos/Jrl_UQcZqOc/download"
      },
      "categories": [],
      "sponsored": false,
      "sponsored_by": null,
      "sponsored_impressions_id": null,
      "likes": 480,
      "liked_by_user": false,
      "current_user_collections": [],
      "slug": null,
      "user": {
        "id": "CkkJtw-ox1I",
        "updated_at": "2018-10-27T06:58:20-04:00",
        "username": "fabulu75",
        "name": "Fabrice Villard",
        "first_name": "Fabrice",
        "last_name": "Villard",
        "twitter_username": null,
        "portfolio_url": "http://www.enclosed.ch",
        "bio": null,
        "location": null,
        "links": {
          "self": "https://api.unsplash.com/users/fabulu75",
          "html": "https://unsplash.com/@fabulu75",
          "photos": "https://api.unsplash.com/users/fabulu75/photos",
          "likes": "https://api.unsplash.com/users/fabulu75/likes",
          "portfolio": "https://api.unsplash.com/users/fabulu75/portfolio",
          "following": "https://api.unsplash.com/users/fabulu75/following",
          "followers": "https://api.unsplash.com/users/fabulu75/followers"
        },
        "profile_image": {
          "small": "https://images.unsplash.com/profile-1533651674518-3723fed8d396?ixlib=rb-0.3.5&q=80&fm=jpg&crop=faces&cs=tinysrgb&fit=crop&h=32&w=32&s=f4d6c77dc1cc7cb474b4c8b63de34c63",
          "medium": "https://images.unsplash.com/profile-1533651674518-3723fed8d396?ixlib=rb-0.3.5&q=80&fm=jpg&crop=faces&cs=tinysrgb&fit=crop&h=64&w=64&s=aaa696e291b5b0500df4cd3fd9623d2b",
          "large": "https://images.unsplash.com/profile-1533651674518-3723fed8d396?ixlib=rb-0.3.5&q=80&fm=jpg&crop=faces&cs=tinysrgb&fit=crop&h=128&w=128&s=cc4382455be0a4d962942ef598b04bf7"
        },
        "instagram_username": null,
        "total_collections": 0,
        "total_likes": 1,
        "total_photos": 70,
        "accepted_tos": false
      },
      "tags": [
        {
          "title": "tree"
        },
        {
          "title": "snow"
        },
        {
          "title": "sky"
        },
        {
          "title": "black and white"
        },
        {
          "title": "nature"
        },
        {
          "title": "outdoors"
        },
        {
          "title": "solitude"
        },
        {
          "title": "solitary"
        },
        {
          "title": "landscape"
        }
      ],
      "photo_tags": [
        {
          "title": "tree"
        },
        {
          "title": "snow"
        },
        {
          "title": "sky"
        },
        {
          "title": "black and white"
        },
        {
          "title": "nature"
        }
      ]
    },
    {
      "id": "YHfFynSrclg",
      "created_at": "2018-02-27T17:29:02-05:00",
      "updated_at": "2018-08-28T20:42:08-04:00",
      "width": 3764,
      "height": 5711,
      "color": "#192022",
      "description": "boat sailing in body of water",
      "urls": {
        "raw": "https://images.unsplash.com/photo-1519770340285-c801df5ff3db?ixlib=rb-0.3.5&ixid=eyJhcHBfaWQiOjQwNDY1fQ&s=986b61d2640519f8d6912963c7e5477e",
        "full": "https://images.unsplash.com/photo-1519770340285-c801df5ff3db?ixlib=rb-0.3.5&q=85&fm=jpg&crop=entropy&cs=srgb&ixid=eyJhcHBfaWQiOjQwNDY1fQ&s=fffec33a254e450bc70a889b61a7a167",
        "regular": "https://images.unsplash.com/photo-1519770340285-c801df5ff3db?ixlib=rb-0.3.5&q=80&fm=jpg&crop=entropy&cs=tinysrgb&w=1080&fit=max&ixid=eyJhcHBfaWQiOjQwNDY1fQ&s=c1538e5b6fc71069062a4dea0e1517b2",
        "small": "https://images.unsplash.com/photo-1519770340285-c801df5ff3db?ixlib=rb-0.3.5&q=80&fm=jpg&crop=entropy&cs=tinysrgb&w=400&fit=max&ixid=eyJhcHBfaWQiOjQwNDY1fQ&s=4dd934ed2bc0ddddfb7a153956b4bb70",
        "thumb": "https://images.unsplash.com/photo-1519770340285-c801df5ff3db?ixlib=rb-0.3.5&q=80&fm=jpg&crop=entropy&cs=tinysrgb&w=200&fit=max&ixid=eyJhcHBfaWQiOjQwNDY1fQ&s=44a790828afaca9e2a6e38ef957f1b6f"
      },
      "links": {
        "self": "https://api.unsplash.com/photos/YHfFynSrclg",
        "html": "https://unsplash.com/photos/YHfFynSrclg",
        "download": "https://unsplash.com/photos/YHfFynSrclg/download",
        "download_location": "https://api.unsplash.com/photos/YHfFynSrclg/download"
      },
      "categories": [],
      "sponsored": false,
      "sponsored_by": null,
      "sponsored_impressions_id": null,
      "likes": 170,
      "liked_by_user": false,
      "current_user_collections": [],
      "slug": null,
      "user": {
        "id": "pJEymXyDH1Y",
        "updated_at": "2018-10-23T17:57:37-04:00",
        "username": "christinaamba",
        "name": "Christina Ambalavanar",
        "first_name": "Christina",
        "last_name": "Ambalavanar",
        "twitter_username": "christina.amba",
        "portfolio_url": "http://christinaamba.com",
        "bio": null,
        "location": "Rochester, NY",
        "links": {
          "self": "https://api.unsplash.com/users/christinaamba",
          "html": "https://unsplash.com/@christinaamba",
          "photos": "https://api.unsplash.com/users/christinaamba/photos",
          "likes": "https://api.unsplash.com/users/christinaamba/likes",
          "portfolio": "https://api.unsplash.com/users/christinaamba/portfolio",
          "following": "https://api.unsplash.com/users/christinaamba/following",
          "followers": "https://api.unsplash.com/users/christinaamba/followers"
        },
        "profile_image": {
          "small": "https://images.unsplash.com/profile-fb-1519769563-dcd979634f7d.jpg?ixlib=rb-0.3.5&q=80&fm=jpg&crop=faces&cs=tinysrgb&fit=crop&h=32&w=32&s=dde3c0ea7c777baa9ae1243c37410e84",
          "medium": "https://images.unsplash.com/profile-fb-1519769563-dcd979634f7d.jpg?ixlib=rb-0.3.5&q=80&fm=jpg&crop=faces&cs=tinysrgb&fit=crop&h=64&w=64&s=4777700f53ea034fc64f4d55a33ac206",
          "large": "https://images.unsplash.com/profile-fb-1519769563-dcd979634f7d.jpg?ixlib=rb-0.3.5&q=80&fm=jpg&crop=faces&cs=tinysrgb&fit=crop&h=128&w=128&s=0b136f6ba08e8d1a49a7e3d77c467910"
        },
        "instagram_username": "christinaamba",
        "total_collections": 0,
        "total_likes": 0,
        "total_photos": 10,
        "accepted_tos": false
      },
      "tags": [
        {
          "title": "sailboat"
        },
        {
          "title": "sea"
        },
        {
          "title": "ocean"
        },
        {
          "title": "sailing"
        },
        {
          "title": "sail"
        },
        {
          "title": "hermosa beach"
        },
        {
          "title": "united states"
        },
        {
          "title": "sky"
        },
        {
          "title": "pacific"
        },
        {
          "title": "clear sky"
        },
        {
          "title": "beach"
        },
        {
          "title": "clear"
        },
        {
          "title": "water"
        },
        {
          "title": "pacific ocean"
        },
        {
          "title": "californium"
        },
        {
          "title": "boat"
        }
      ],
      "photo_tags": [
        {
          "title": "sailboat"
        },
        {
          "title": "sea"
        },
        {
          "title": "ocean"
        },
        {
          "title": "sailing"
        },
        {
          "title": "sail"
        }
      ]
    },
    {
      "id": "5E5N49RWtbA",
      "created_at": "2017-05-08T10:20:14-04:00",
      "updated_at": "2018-10-09T12:16:14-04:00",
      "width": 5184,
      "height": 3456,
      "color": "#DBE493",
      "description": "blue lemon sliced into two halves",
      "urls": {
        "raw": "https://images.unsplash.com/photo-1494253109108-2e30c049369b?ixlib=rb-0.3.5&ixid=eyJhcHBfaWQiOjQwNDY1fQ&s=8867119a06ee5712ec187112d9cf5191",
        "full": "https://images.unsplash.com/photo-1494253109108-2e30c049369b?ixlib=rb-0.3.5&q=85&fm=jpg&crop=entropy&cs=srgb&ixid=eyJhcHBfaWQiOjQwNDY1fQ&s=3f30d3d5d378633a54b9af9444cff9f7",
        "regular": "https://images.unsplash.com/photo-1494253109108-2e30c049369b?ixlib=rb-0.3.5&q=80&fm=jpg&crop=entropy&cs=tinysrgb&w=1080&fit=max&ixid=eyJhcHBfaWQiOjQwNDY1fQ&s=d04812510a7fbdc939ea3ab000846cf3",
        "small": "https://images.unsplash.com/photo-1494253109108-2e30c049369b?ixlib=rb-0.3.5&q=80&fm=jpg&crop=entropy&cs=tinysrgb&w=400&fit=max&ixid=eyJhcHBfaWQiOjQwNDY1fQ&s=b75e24059b909228e7c817b34808d1e1",
        "thumb": "https://images.unsplash.com/photo-1494253109108-2e30c049369b?ixlib=rb-0.3.5&q=80&fm=jpg&crop=entropy&cs=tinysrgb&w=200&fit=max&ixid=eyJhcHBfaWQiOjQwNDY1fQ&s=5b3e3f7575dd5be300b09da21f552c10"
      },
      "links": {
        "self": "https://api.unsplash.com/photos/5E5N49RWtbA",
        "html": "https://unsplash.com/photos/5E5N49RWtbA",
        "download": "https://unsplash.com/photos/5E5N49RWtbA/download",
        "download_location": "https://api.unsplash.com/photos/5E5N49RWtbA/download"
      },
      "categories": [],
      "sponsored": false,
      "sponsored_by": null,
      "sponsored_impressions_id": null,
      "likes": 1765,
      "liked_by_user": false,
      "current_user_collections": [],
      "slug": null,
      "user": {
        "id": "ijAkU6InnYY",
        "updated_at": "2018-10-27T17:36:11-04:00",
        "username": "codytdavis",
        "name": "Cody Davis",
        "first_name": "Cody",
        "last_name": "Davis",
        "twitter_username": null,
        "portfolio_url": "http://www.codydavisdesign.com",
        "bio": "I'm a Graphic Designer with a passion for photography! I love space and color, if you couldn't tell by my profile. I'm available for hire if anyone wants to do a shoot within a states drive of Virginia! Tag me on Instagram!",
        "location": null,
        "links": {
          "self": "https://api.unsplash.com/users/codytdavis",
          "html": "https://unsplash.com/@codytdavis",
          "photos": "https://api.unsplash.com/users/codytdavis/photos",
          "likes": "https://api.unsplash.com/users/codytdavis/likes",
          "portfolio": "https://api.unsplash.com/users/codytdavis/portfolio",
          "following": "https://api.unsplash.com/users/codytdavis/following",
          "followers": "https://api.unsplash.com/users/codytdavis/followers"
        },
        "profile_image": {
          "small": "https://images.unsplash.com/profile-1539101478291-b33ad66d6f2e?ixlib=rb-0.3.5&q=80&fm=jpg&crop=faces&cs=tinysrgb&fit=crop&h=32&w=32&s=027c3a490c60881247c0873fee11184a",
          "medium": "https://images.unsplash.com/profile-1539101478291-b33ad66d6f2e?ixlib=rb-0.3.5&q=80&fm=jpg&crop=faces&cs=tinysrgb&fit=crop&h=64&w=64&s=ed552bc14616df22466da84ed7398f44",
          "large": "https://images.unsplash.com/profile-1539101478291-b33ad66d6f2e?ixlib=rb-0.3.5&q=80&fm=jpg&crop=faces&cs=tinysrgb&fit=crop&h=128&w=128&s=89b811eefce71cabe2dca2b10b4f0e4e"
        },
        "instagram_username": "cody.davis.design",
        "total_collections": 0,
        "total_likes": 2825,
        "total_photos": 14,
        "accepted_tos": false
      },
      "tags": [
        {
          "title": "blue"
        },
        {
          "title": "fruit"
        },
        {
          "title": "yellow"
        },
        {
          "title": "bold"
        },
        {
          "title": "half"
        },
        {
          "title": "cut"
        },
        {
          "title": "orange"
        },
        {
          "title": "contrast"
        },
        {
          "title": "compliment"
        },
        {
          "title": "funny"
        },
        {
          "title": "unique"
        },
        {
          "title": "interesting"
        },
        {
          "title": "fun"
        },
        {
          "title": "surreal"
        },
        {
          "title": "abstract"
        },
        {
          "title": "minimalist"
        },
        {
          "title": "sliced"
        },
        {
          "title": "paint"
        },
        {
          "title": "blue paint"
        }
      ],
      "photo_tags": [
        {
          "title": "blue"
        },
        {
          "title": "fruit"
        },
        {
          "title": "yellow"
        },
        {
          "title": "bold"
        },
        {
          "title": "half"
        }
      ]
    },
    {
      "id": "Sg7eWHKrxrA",
      "created_at": "2018-01-10T09:54:05-05:00",
      "updated_at": "2018-08-28T20:38:34-04:00",
      "width": 3456,
      "height": 5184,
      "color": "#1A1B16",
      "description": "close-up photo of green leaf",
      "urls": {
        "raw": "https://images.unsplash.com/photo-1515595967223-f9fa59af5a3b?ixlib=rb-0.3.5&ixid=eyJhcHBfaWQiOjQwNDY1fQ&s=e9373b3da6e2d6db8ba1125d92393d10",
        "full": "https://images.unsplash.com/photo-1515595967223-f9fa59af5a3b?ixlib=rb-0.3.5&q=85&fm=jpg&crop=entropy&cs=srgb&ixid=eyJhcHBfaWQiOjQwNDY1fQ&s=ab0158373fb2714c80046cb5cf54f3bc",
        "regular": "https://images.unsplash.com/photo-1515595967223-f9fa59af5a3b?ixlib=rb-0.3.5&q=80&fm=jpg&crop=entropy&cs=tinysrgb&w=1080&fit=max&ixid=eyJhcHBfaWQiOjQwNDY1fQ&s=7fc48a95693f2501711334a6e3dfd7e7",
        "small": "https://images.unsplash.com/photo-1515595967223-f9fa59af5a3b?ixlib=rb-0.3.5&q=80&fm=jpg&crop=entropy&cs=tinysrgb&w=400&fit=max&ixid=eyJhcHBfaWQiOjQwNDY1fQ&s=98cc2b5f5318ce8b3ec590a4316fa85a",
        "thumb": "https://images.unsplash.com/photo-1515595967223-f9fa59af5a3b?ixlib=rb-0.3.5&q=80&fm=jpg&crop=entropy&cs=tinysrgb&w=200&fit=max&ixid=eyJhcHBfaWQiOjQwNDY1fQ&s=db190531f4ecf9f37bd8eb432341feee"
      },
      "links": {
        "self": "https://api.unsplash.com/photos/Sg7eWHKrxrA",
        "html": "https://unsplash.com/photos/Sg7eWHKrxrA",
        "download": "https://unsplash.com/photos/Sg7eWHKrxrA/download",
        "download_location": "https://api.unsplash.com/photos/Sg7eWHKrxrA/download"
      },
      "categories": [],
      "sponsored": false,
      "sponsored_by": null,
      "sponsored_impressions_id": null,
      "likes": 762,
      "liked_by_user": false,
      "current_user_collections": [],
      "slug": null,
      "user": {
        "id": "MCNKkrZVUh0",
        "updated_at": "2018-09-25T16:19:49-04:00",
        "username": "chuabingquan",
        "name": "Chua Bing Quan",
        "first_name": "Chua",
        "last_name": "Bing Quan",
        "twitter_username": null,
        "portfolio_url": null,
        "bio": null,
        "location": null,
        "links": {
          "self": "https://api.unsplash.com/users/chuabingquan",
          "html": "https://unsplash.com/@chuabingquan",
          "photos": "https://api.unsplash.com/users/chuabingquan/photos",
          "likes": "https://api.unsplash.com/users/chuabingquan/likes",
          "portfolio": "https://api.unsplash.com/users/chuabingquan/portfolio",
          "following": "https://api.unsplash.com/users/chuabingquan/following",
          "followers": "https://api.unsplash.com/users/chuabingquan/followers"
        },
        "profile_image": {
          "small": "https://images.unsplash.com/profile-fb-1515595922-3b9fb8b94a78.jpg?ixlib=rb-0.3.5&q=80&fm=jpg&crop=faces&cs=tinysrgb&fit=crop&h=32&w=32&s=1d1ca550ee5398baeff427e43a667395",
          "medium": "https://images.unsplash.com/profile-fb-1515595922-3b9fb8b94a78.jpg?ixlib=rb-0.3.5&q=80&fm=jpg&crop=faces&cs=tinysrgb&fit=crop&h=64&w=64&s=ced9a76c4961e4777e553de2486d80ac",
          "large": "https://images.unsplash.com/profile-fb-1515595922-3b9fb8b94a78.jpg?ixlib=rb-0.3.5&q=80&fm=jpg&crop=faces&cs=tinysrgb&fit=crop&h=128&w=128&s=7fcdfd2763abefb8ba3ae381853e92ba"
        },
        "instagram_username": null,
        "total_collections": 0,
        "total_likes": 12,
        "total_photos": 5
      },
      "tags": [
        {
          "title": "tropical"
        },
        {
          "title": "succulent"
        },
        {
          "title": "spike"
        },
        {
          "title": "spiky"
        },
        {
          "title": "white"
        },
        {
          "title": "nature"
        },
        {
          "title": "plant"
        },
        {
          "title": "green"
        },
        {
          "title": "fresh"
        },
        {
          "title": "simple"
        },
        {
          "title": "clean"
        },
        {
          "title": "modern"
        },
        {
          "title": "background"
        },
        {
          "title": "leaf"
        },
        {
          "title": "agave"
        },
        {
          "title": "leafe"
        }
      ],
      "photo_tags": [
        {
          "title": "tropical"
        },
        {
          "title": "succulent"
        },
        {
          "title": "spike"
        },
        {
          "title": "spiky"
        },
        {
          "title": "white"
        }
      ]
    }
  ]
}